pyfritz/__init__.py
pyfritz/example.py
pyfritz/py.typed
pyfritz-0.1.0.dist-info/LICENSE
pyfritz-0.1.0.dist-info/WHEEL
pyfritz-0.1.0.dist-info/METADATA
pyfritz-0.1.0.dist-info/RECORD
